BarteReportAPI/__init__.py
BarteReportAPI/main.py
BartePaySDK-0.1.0.dist-info/LICENSE
BartePaySDK-0.1.0.dist-info/METADATA
BartePaySDK-0.1.0.dist-info/WHEEL
BartePaySDK-0.1.0.dist-info/top_level.txt
BartePaySDK-0.1.0.dist-info/RECORD
