Metadata-Version: 2.1
Name: BartePaySDK
Version: 0.1.0
Summary: SDK para interação com a API da Barte.
Home-page: UNKNOWN
Author: Wilson Nadim
Author-email: wilson@barte.com
License: MIT
Keywords: barte pay sdk
Platform: UNKNOWN
Requires-Dist: requests
